setup.py
underverse/__init__.py
underverse/handlers.py
underverse/model.py
underverse/ordereddict.py
underverse/predicates.py
underverse.egg-info/PKG-INFO
underverse.egg-info/SOURCES.txt
underverse.egg-info/dependency_links.txt
underverse.egg-info/requires.txt
underverse.egg-info/top_level.txt
underverse/tests/find_tests.py
underverse/tests/kv_test.py
underverse/tests/load_tests.py
underverse/tests/mapreduce_tests.py
underverse/tests/run_all_tests.py
underverse/tests/speed_test.py
underverse/tests/test_data_gen.py
underverse/tests/find_tests.py
underverse/tests/kv_test.py
underverse/tests/load_tests.py
underverse/tests/mapreduce_tests.py
underverse/tests/run_all_tests.py
underverse/tests/speed_test.py
underverse/tests/test_data_gen.py