Metadata-Version: 1.0
Name: underverse
Version: 0.4.1
Summary: A zero-configuration, non-distributed, JSON-based document storage and analysis module focusing on the manipulation,                     grouping and filtering of unstructured data from various sources. MapReduce is also supported for more advanced                     analysis methods. Query syntax is similar to SQL-Alchemy's filter method.
Home-page: http://packages.python.org/underverse
Author: Max Franks
Author-email: eliquious@gmail.com
License: MIT
Keywords: unstructured data analysis nosql map reduce mapreduce sql alchemy
Platform: UNKNOWN
Classifier: Development Status :: 4 - Beta
Classifier: Natural Language :: English
Classifier: Topic :: Scientific/Engineering :: Information Analysis
Classifier: License :: OSI Approved :: MIT License
